bech32m_chia/__init__.py
bech32m_chia/bech32m.py
bech32m_chia-1.0.3.dist-info/LICENSE
bech32m_chia-1.0.3.dist-info/METADATA
bech32m_chia-1.0.3.dist-info/WHEEL
bech32m_chia-1.0.3.dist-info/top_level.txt
bech32m_chia-1.0.3.dist-info/RECORD
